{"cameraMode":{"drawMode":0,"name":"Shaded","section":"Shading Mode"},"sceneLighting":true,"audioPlay":false,"sceneViewState":{"showFog":true,"showMaterialUpdate":false,"showSkybox":true,"showFlares":true,"showImageEffects":true,"showParticleSystems":true},"in2DMode":false,"pivot":{"x":12.099998474121094,"y":0.6586722731590271,"z":27.700000762939454},"rotation":{"x":-0.30063387751579287,"y":0.21583551168441773,"z":-0.07004616409540177,"w":-0.9263519644737244},"size":5.098026275634766,"orthographic":false}